numpy/LICENSE.txt
numpy/__config__.py
numpy/__init__.py
numpy/_distributor_init.py
numpy/_globals.py
numpy/_pytesttester.py
numpy/conftest.py
numpy/ctypeslib.py
numpy/dual.py
numpy/matlib.py
numpy/setup.py
numpy/version.py
numpy/compat/__init__.py
numpy/compat/_inspect.py
numpy/compat/py3k.py
numpy/compat/setup.py
numpy/compat/tests/__init__.py
numpy/compat/tests/test_compat.py
numpy/core/__init__.py
numpy/core/_add_newdocs.py
numpy/core/_aliased_types.py
numpy/core/_asarray.py
numpy/core/_dtype.py
numpy/core/_dtype_ctypes.py
numpy/core/_dummy.cpython-37m-mips64el-linux-gnuabi64.so
numpy/core/_exceptions.py
numpy/core/_internal.py
numpy/core/_methods.py
numpy/core/_multiarray_tests.cpython-37m-mips64el-linux-gnuabi64.so
numpy/core/_multiarray_umath.cpython-37m-mips64el-linux-gnuabi64.so
numpy/core/_operand_flag_tests.cpython-37m-mips64el-linux-gnuabi64.so
numpy/core/_rational_tests.cpython-37m-mips64el-linux-gnuabi64.so
numpy/core/_string_helpers.py
numpy/core/_struct_ufunc_tests.cpython-37m-mips64el-linux-gnuabi64.so
numpy/core/_type_aliases.py
numpy/core/_ufunc_config.py
numpy/core/_umath_tests.cpython-37m-mips64el-linux-gnuabi64.so
numpy/core/arrayprint.py
numpy/core/cversions.py
numpy/core/defchararray.py
numpy/core/einsumfunc.py
numpy/core/fromnumeric.py
numpy/core/function_base.py
numpy/core/generate_numpy_api.py
numpy/core/getlimits.py
numpy/core/info.py
numpy/core/machar.py
numpy/core/memmap.py
numpy/core/multiarray.py
numpy/core/numeric.py
numpy/core/numerictypes.py
numpy/core/overrides.py
numpy/core/records.py
numpy/core/setup.py
numpy/core/setup_common.py
numpy/core/shape_base.py
numpy/core/umath.py
numpy/core/umath_tests.py
numpy/core/include/numpy/__multiarray_api.h
numpy/core/include/numpy/__ufunc_api.h
numpy/core/include/numpy/_neighborhood_iterator_imp.h
numpy/core/include/numpy/_numpyconfig.h
numpy/core/include/numpy/arrayobject.h
numpy/core/include/numpy/arrayscalars.h
numpy/core/include/numpy/halffloat.h
numpy_mips64-1.17.4.dist-info/LICENSE.txt
numpy_mips64-1.17.4.dist-info/LICENSES_bundled.txt
numpy_mips64-1.17.4.dist-info/METADATA
numpy_mips64-1.17.4.dist-info/WHEEL
numpy_mips64-1.17.4.dist-info/entry_points.txt
numpy_mips64-1.17.4.dist-info/top_level.txt
numpy_mips64-1.17.4.dist-info/RECORD
